hubris/__init__.py
hubris/channel.py
hubris/hub.py
hubris/publisher.py
hubris/subscriber.py
hubris/subscription.py
hubris/util.py
hubris-0.0.4.dist-info/LICENSE
hubris-0.0.4.dist-info/METADATA
hubris-0.0.4.dist-info/WHEEL
hubris-0.0.4.dist-info/top_level.txt
hubris-0.0.4.dist-info/RECORD
