Metadata-Version: 2.1
Name: hubris
Version: 0.0.4
Summary: Hubris is a simple library for implementing inter-process communication (IPC) between separate Python processes. It's based on named pipes created by the POSIX `mkfifo` system call.
Home-page: https://github.com/gigaquads/hubris.git
Author: Gigaquads
Author-email: what@gigaquads.com
License: UNKNOWN
Platform: UNKNOWN
Classifier: Programming Language :: Python :: 3.9
Classifier: License :: OSI Approved :: MIT License
Requires-Dist: appyratus
Requires-Dist: pytest
